{
    "run_id": "dfc84fec-9f92-40a3-9e15-1958fe9e9e4e",
    "timestamp": "2025-05-05T00:13:31.082430",
    "influencer_count": 1,
    "influencers": [
        "vivianssf"
    ],
    "countries": [
        "Other"
    ],
    "snapshot": {
        "vivianssf": {
            "username": "vivianssf",
            "full_name": "Vivian Soo",
            "biography": "Foodie \ud83c\udf7d\ufe0f | Coffee \u2615 | Lifestyle \ud83c\udfd6\ufe0f\nTraveller \u2708\ufe0f",
            "external_url": "",
            "followers_count": 1836,
            "follows_count": 773,
            "is_verified": false,
            "posts_count": 1503,
            "profile_pic_url": "https://scontent-atl3-1.cdninstagram.com/v/t51.2885-19/470921974_523755200644668_8387871918995072678_n.jpg?stp=dst-jpg_e0_s150x150_tt6&_nc_ht=scontent-atl3-1.cdninstagram.com&_nc_cat=100&_nc_oc=Q6cZ2QH10YK7f1bWzYl-jOGHKBGrmJaKCJXu2pVm841uHTfSgRcC-lrQR8JIJF24PqCFH-OiVPM0XdYunLmXNsZ98aGS&_nc_ohc=GzkHke11lB0Q7kNvwG5LWIz&_nc_gid=QoL5r_U9NiCTqxOIgjEwIw&edm=AOQ1c0wBAAAA&ccb=7-5&oh=00_AfFMP6bPzLBJqyGNAOZy0FShPFbfTVsk3AH-zdIAacaQBA&oe=681D9069&_nc_sid=8b3546",
            "business_category": "",
            "country": "Other",
            "processed_at": "2025-05-05 00:13:26",
            "posts": [
                {
                    "id": "sc_DItj_9oJyRA",
                    "shortcode": "DItj_9oJyRA",
                    "caption": "Brunch kissed with local flavours \u2014 simple, soulful, satisfying.  @ryn_cafe \u2615\ufe0f\ud83c\udf5b\u2728\n\n.\n.\n.\n.\n.\n#cafevibes #cafemy #cafehunt #cafeteller #subangcafe #cafeyouneed #coffeesesh #coffeegeek #cafeyouneed #coffeeshopvibes #masfotokopi #baristadaily #eatnowkl #coffeefliicks #malaysiancafes #mycafefood #cafedesign #cafeinterior #malaysialocalfoods #coffeeshopcorners #klcafehop #eeeeeeats #kleats #cafehoppingmalaysia #likeforlikes #cafeculturekl #brunchtime #postitforaesthetics #klnow #feedfeed #cafestagra\uff4d",
                    "likes_count": 47,
                    "comments_count": 1,
                    "timestamp": "2025-04-21T14:26:14.000Z",
                    "display_url": "https://scontent-atl3-1.cdninstagram.com/v/t51.2885-15/491468391_18503817514045794_7050635927911509503_n.jpg?stp=dst-jpg_e35_p1080x1080_sh0.08_tt6&_nc_ht=scontent-atl3-1.cdninstagram.com&_nc_cat=106&_nc_oc=Q6cZ2QEFk_u4Xyyu4qXjIDobd2LSmX5uNgUivIw4gXY84LWALmhm2dhpYPOVMcCavmQ-0frpA0R3j6Ao7RGHDPk60khb&_nc_ohc=O5IFZEeJr1cQ7kNvwF5HU-C&_nc_gid=_WU4QNIk1auhq5qAdEuX4Q&edm=APs17CUBAAAA&ccb=7-5&oh=00_AfH__a7BOULt6JgKkF3vA3GEbSPPaBUXQN8NfXZLba9vNw&oe=681D8E54&_nc_sid=10d13b",
                    "is_video": false,
                    "image_local": "images/user_2/posts/sc_DItj_9oJyRA.jpg",
                    "engagement_rate": 2.6143790849673203,
                    "hashtags": [
                        "cafevibes",
                        "cafemy",
                        "cafehunt",
                        "cafeteller",
                        "subangcafe",
                        "cafeyouneed",
                        "coffeesesh",
                        "coffeegeek",
                        "cafeyouneed",
                        "coffeeshopvibes",
                        "masfotokopi",
                        "baristadaily",
                        "eatnowkl",
                        "coffeefliicks",
                        "malaysiancafes",
                        "mycafefood",
                        "cafedesign",
                        "cafeinterior",
                        "malaysialocalfoods",
                        "coffeeshopcorners",
                        "klcafehop",
                        "eeeeeeats",
                        "kleats",
                        "cafehoppingmalaysia",
                        "likeforlikes",
                        "cafeculturekl",
                        "brunchtime",
                        "postitforaesthetics",
                        "klnow",
                        "feedfeed",
                        "cafestagra\uff4d"
                    ]
                },
                {
                    "id": "sc_DIyvVOByIw4",
                    "shortcode": "DIyvVOByIw4",
                    "caption": "Tucked in a hidden caf\u00e9 with a cup of quality matcha it\u2019s brewed perfectly. \ud83c\udf75\u2728\ud83c\udf34\ud83c\udf33 @jamescoffee_my \n\n.\n.\n.\n.\n.\n.\n#hiddencafe #cafemy #cafeteller #cafehopmy #cafepj #coffeegeek #cafeyouneed #coffeesesh #malaysiancafes #cafestagra\uff4d #cafedesign #cafedecor #postitforaesthetics #cafeinterior #minimalist #klcafehop #coffeefliicks #baristadaily #masfotokopi #likesforlike #cafeculturekl #klnow #cafelife #caffeindaily #dailycortado #coffeeshopvibes #cafehunt #coffeemeetbojio #cafeinspo #caffeincouture",
                    "likes_count": 64,
                    "comments_count": 5,
                    "timestamp": "2025-04-23T14:41:28.000Z",
                    "display_url": "https://instagram.fkhi2-2.fna.fbcdn.net/v/t51.2885-15/491470087_18504150658045794_4710516863526345889_n.jpg?stp=dst-jpg_e35_p1080x1080_sh0.08_tt6&_nc_ht=instagram.fkhi2-2.fna.fbcdn.net&_nc_cat=106&_nc_oc=Q6cZ2QE0JMys4TvV3wfzW1gYFsfCOlZ4K-z-lrC6P7H9oGoUN21H0YkA7ziJFknHfcGyYKc&_nc_ohc=gLMcSB3YGOUQ7kNvwGrSY2c&_nc_gid=eUqdguRcWsew7a2m9syPcA&edm=APs17CUBAAAA&ccb=7-5&oh=00_AfE_pNbVZG-DTs71WHVttDdZTTm0ChzxNbz_0-d9dwfY9w&oe=681D7CE1&_nc_sid=10d13b",
                    "is_video": false,
                    "image_local": "images/user_2/posts/sc_DIyvVOByIw4.jpg",
                    "engagement_rate": 3.758169934640523,
                    "hashtags": [
                        "hiddencafe",
                        "cafemy",
                        "cafeteller",
                        "cafehopmy",
                        "cafepj",
                        "coffeegeek",
                        "cafeyouneed",
                        "coffeesesh",
                        "malaysiancafes",
                        "cafestagra\uff4d",
                        "cafedesign",
                        "cafedecor",
                        "postitforaesthetics",
                        "cafeinterior",
                        "minimalist",
                        "klcafehop",
                        "coffeefliicks",
                        "baristadaily",
                        "masfotokopi",
                        "likesforlike",
                        "cafeculturekl",
                        "klnow",
                        "cafelife",
                        "caffeindaily",
                        "dailycortado",
                        "coffeeshopvibes",
                        "cafehunt",
                        "coffeemeetbojio",
                        "cafeinspo",
                        "caffeincouture"
                    ]
                }
            ],
            "profile_pic_local": "images/user_2/profiles/vivianssf.jpg"
        }
    }
}